svx/__init__.py
svx/cli.py
svx/core/__init__.py
svx/core/audio.py
svx/core/clipboard.py
svx/core/config.py
svx/core/pipeline.py
svx/core/prompt.py
svx/core/storage.py
svx/providers/__init__.py
svx/providers/base.py
svx/providers/mistral.py
svx/ui/qt_app.py
supervoxtral-0.1.5.dist-info/METADATA
supervoxtral-0.1.5.dist-info/WHEEL
supervoxtral-0.1.5.dist-info/entry_points.txt
supervoxtral-0.1.5.dist-info/licenses/LICENSE
supervoxtral-0.1.5.dist-info/RECORD
