Metadata-Version: 2.4
Name: supervoxtral
Version: 0.1.5
Summary: CLI/GUI audio recorder and transcription client using Mistral Voxtral (chat with audio and transcription).
License: MIT
License-File: LICENSE
Keywords: audio,cli,gui,mistral,transcription,voxtral,whisper
Requires-Python: >=3.11
Requires-Dist: mistralai
Requires-Dist: pyperclip
Requires-Dist: python-dotenv
Requires-Dist: rich
Requires-Dist: sounddevice
Requires-Dist: soundfile
Requires-Dist: typer
Provides-Extra: dev
Requires-Dist: black; extra == 'dev'
Requires-Dist: mypy; extra == 'dev'
Requires-Dist: pytest; extra == 'dev'
Requires-Dist: ruff; extra == 'dev'
Requires-Dist: types-python-dotenv; extra == 'dev'
Provides-Extra: gui
Requires-Dist: pyside6-essentials; extra == 'gui'
